[{"id": "1321", "name": "金运路"}, {"id": "1322", "name": "金沙江西路"}, {"id": "1323", "name": "丰庄"}, {"id": "1324", "name": "祁连山南路"}, {"id": "1325", "name": "真北路"}, {"id": "1326", "name": "大渡河路"}, {"id": "1327", "name": "金沙江路"}, {"id": "1328", "name": "隆德路"}, {"id": "1329", "name": "武宁路"}, {"id": "1330", "name": "长寿路"}, {"id": "1331", "name": "江宁路"}, {"id": "1332", "name": "汉中路"}, {"id": "1333", "name": "自然博物馆"}, {"id": "1334", "name": "南京西路"}, {"id": "1335", "name": "淮海中路"}, {"id": "1336", "name": "新天地"}, {"id": "1337", "name": "马当路"}, {"id": "1338", "name": "世博会博物馆"}, {"id": "1339", "name": "世博大道"}]